{
  "name": "Common Vulnerability Scoring System V2",
  "type": "cvssv2",
  "description": "The Common Vulnerability Scoring System V2 object describes the base metrics as defined by the National Institute of Standards and Technology (NIST). See <a target='_blank' href='https://nvd.nist.gov/vuln-metrics/cvss/v2-calculator'>Common Vulnerability Scoring System</a> for more information.",
  "attributes": {
    "access_complexity_id": {
      "requirement": "required",
      "enum": {
        "0": {
          "name": "Unknown"
        },
        "1": {
          "name": "Low"
        },
        "2": {
          "name": "Medium"
        },
        "3": {
          "name": "High"
        }
      }
    },
    "attack_vector_id": {
      "requirement": "required",
      "enum": {
        "0": {
          "name": "Unknown"
        },
        "1": {
          "name": "Local Access"
        },
        "2": {
          "name": "Adjacent Network Access"
        },
        "3": {
          "name": "Network Accessible"
        }
      }
    },
    "authentication_id": {
      "requirement": "required",
      "enum": {
        "0": {
          "name": "Unknown"
        },
        "1": {
          "name": "Multiple Instances"
        },
        "2": {
          "name": "Single Instance"
        },
        "3": {
          "name": "No Authentication"
        }
      }
    },
    "availability_impact_id": {
      "requirement": "required",
      "enum": {
        "0": {
          "name": "Unknown"
        },
        "1": {
          "name": "No Impact"
        },
        "2": {
          "name": "Partial"
        },
        "3": {
          "name": "Complete"
        }
      }
    },
    "confidentiality_impact_id": {
      "requirement": "required",
      "enum": {
        "0": {
          "name": "Unknown"
        },
        "1": {
          "name": "No Impact"
        },
        "2": {
          "name": "Partial"
        },
        "3": {
          "name": "Complete"
        }
      }
    },
    "integrity_impact_id": {
      "requirement": "required",
      "enum": {
        "0": {
          "name": "Unknown"
        },
        "1": {
          "name": "No Impact"
        },
        "2": {
          "name": "Partial"
        },
        "3": {
          "name": "Complete"
        }
      }
    },
    "risk": {
      "requirement": "required"
    }
  }
}