{
  "description": "Related Findings object describes findings related to a finding as identified by the security product.",
  "caption": "Related Findings",
  "name": "related_findings",
  "extends": "object",
  "attributes": {
    "product_uid": {
      "description": "The unique identifier of the product that reported the finding.",
      "requirement": "optional"
    },
    "uid": {
      "description": "The unique identifier of the related finding.",
      "requirement": "required"
    }
  }
}
