{
  "attributes": {
    "$include": "traits/network_http_connection.json",
    "traffic": {
      "requirement": "optional"
    }
  },
  "description": "Endpoint HTTP Alert events report the detections of malware in the network HTTP traffic.",
  "extends": "endpoint_network_traffic_alert",
  "name": "Endpoint HTTP Alert",
  "see_also": [
    "endpoint_network_http_activity",
    "endpoint_network_connection_alert",
    "endpoint_network_traffic_alert",
    "network_http_alert"
  ],
  "type": "endpoint_network_http_alert",
  "uid": 511
}