{
  "caption": "Windows Resource",
  "description": "The Windows resource object describes a resource object managed by Windows, such as mutant or timer.",
  "extends": "_resource",
  "name": "win_resource",
  "attributes": {
    "details": {
      "description": "The string detailing the attributes of the resource object.",
      "requirement": "optional"
    },
    "name": {
      "description": "The name of the resource object."
    },
    "svc_name": {
      "description": "The Windows service acting as the object server for the resource object, such as Security or Security Account Manager.",
      "requirement": "optional"
    },
    "type": {
      "description": "The type of the Windows resource object.",
      "requirement": "optional"
    },
    "type_id": {
      "description": "The normalized type identifier of the Windows resource object accessed.",
      "requirement": "required",
      "sibling": "type",
      "type": "integer_t",
      "enum": {
        "0": {
          "caption": "Unknown",
          "description": "The resource object type is unknown."
        },
        "1": {
          "caption": "Directory",
          "references": [
            {
              "description": "Object Manager Directory Objects",
              "url": "https://learn.microsoft.com/en-us/windows-hardware/drivers/kernel/object-directories"
            }
          ]
        },
        "2": {
          "caption": "Event",
          "references": [
            {
              "description": "Event Objects and CreateEvent Function",
              "url": "https://learn.microsoft.com/en-us/windows/win32/sync/event-objects"
            }
          ]
        },
        "3": {
          "caption": "Timer",
          "references": [
            {
              "description": "Timer Objects and CreateWaitableTimer Function",
              "url": "https://learn.microsoft.com/en-us/windows/win32/sync/waitable-timer-objects"
            }
          ]
        },
        "4": {
          "caption": "Device",
          "references": [
            {
              "description": "Device Objects and I/O Manager",
              "url": "https://learn.microsoft.com/en-us/windows-hardware/drivers/kernel/device-objects-and-device-stacks"
            }
          ]
        },
        "5": {
          "caption": "Mutant",
          "references": [
            {
              "description": "Mutex Objects and CreateMutex Function",
              "url": "https://learn.microsoft.com/en-us/windows/win32/sync/mutex-objects"
            }
          ]
        },
        "6": {
          "caption": "Type"
        },
        "7": {
          "caption": "File",
          "references": [
            {
              "description": "File objects",
              "url": "https://learn.microsoft.com/en-us/windows/win32/fileio/file-objects"
            }
          ]
        },
        "8": {
          "caption": "Token",
          "references": [
            {
              "description": "Access Tokens and Token objects",
              "url": "https://learn.microsoft.com/en-us/windows/win32/secauthz/access-tokens"
            }
          ]
        },
        "9": {
          "caption": "Thread",
          "references": [
            {
              "description": "Thread Objects and CreateThread Function",
              "url": "https://learn.microsoft.com/en-us/windows/win32/procthread/creating-threads"
            }
          ]
        },
        "10": {
          "caption": "Section",
          "references": [
            {
              "description": "Section object",
              "url": "https://learn.microsoft.com/en-us/windows-hardware/drivers/kernel/section-objects-and-views"
            }
          ]
        },
        "11": {
          "caption": "WindowStation",
          "references": [
            {
              "description": "Window Station objects",
              "url": "https://learn.microsoft.com/en-us/windows/win32/winstation/window-stations"
            }
          ]
        },
        "12": {
          "caption": "DebugObject"
        },
        "13": {
          "caption": "FilterCommunicationPort"
        },
        "14": {
          "caption": "EventPair"
        },
        "15": {
          "caption": "Driver",
          "references": [
            {
              "description": "Driver objects",
              "url": "https://learn.microsoft.com/en-us/windows-hardware/drivers/kernel/introduction-to-driver-objects"
            }
          ]
        },
        "16": {
          "caption": "IoCompletion",
          "references": [
            {
              "description": "I/O Completion Ports",
              "url": "https://learn.microsoft.com/en-us/windows/win32/fileio/i-o-completion-ports"
            }
          ]
        },
        "17": {
          "caption": "Controller",
          "references": [
            {
              "description": "Controller objects",
              "url": "https://learn.microsoft.com/en-us/windows-hardware/drivers/kernel/introduction-to-controller-objects"
            }
          ]
        },
        "18": {
          "caption": "SymbolicLink",
          "references": [
            {
              "description": "mklink function",
              "url": "https://learn.microsoft.com/en-us/windows-server/administration/windows-commands/mklink"
            }
          ]
        },
        "19": {
          "caption": "WmiGuid",
          "references": [
            {
              "description": "WMI Class Qualifiers",
              "url": "https://learn.microsoft.com/en-us/windows-hardware/drivers/kernel/wmi-class-qualifiers"
            }
          ]
        },
        "20": {
          "caption": "Process",
          "references": [
            {
              "description": "Process objects and CreateProcess Function",
              "url": "https://learn.microsoft.com/en-us/windows/win32/procthread/creating-processes"
            }
          ]
        },
        "21": {
          "caption": "Profile",
          "references": [
            {
              "description": "User Profile objects",
              "url": "https://learn.microsoft.com/en-us/windows/win32/shell/user-profiles"
            }
          ]
        },
        "22": {
          "caption": "Desktop",
          "references": [
            {
              "description": "Desktop objects",
              "url": "https://learn.microsoft.com/en-us/windows/win32/winstation/desktops"
            }
          ]
        },
        "23": {
          "caption": "KeyedEvent",
          "references": [
            {
              "description": "NTAPI Keyed Events",
              "url": "http://undocumented.ntinternals.net/index.html?page=UserMode%2FUndocumented%20Functions%2FNT%20Objects%2FKeyedEvent%2FNtCreateKeyedEvent.html"
            }
          ]
        },
        "24": {
          "caption": "Adapter",
          "references": [
            {
              "description": "Adapter objects",
              "url": "https://learn.microsoft.com/en-us/windows-hardware/drivers/kernel/adapter-objects-and-dma"
            }
          ]
        },
        "25": {
          "caption": "Key"
        },
        "26": {
          "caption": "WaitablePort"
        },
        "27": {
          "caption": "Callback",
          "references": [
            {
              "description": "Callback objects",
              "url": "https://learn.microsoft.com/en-us/windows-hardware/drivers/kernel/callback-objects"
            }
          ]
        },
        "28": {
          "caption": "Semaphore",
          "references": [
            {
              "description": "Semaphore objects and CreateSemaphore Function",
              "url": "https://learn.microsoft.com/en-us/windows/win32/sync/semaphore-objects"
            }
          ]
        },
        "29": {
          "caption": "Job",
          "references": [
            {
              "description": "Job objects and CreateJobObject Function",
              "url": "https://learn.microsoft.com/en-us/windows/win32/procthread/job-objects"
            }
          ]
        },
        "30": {
          "caption": "Port"
        },
        "31": {
          "caption": "FilterConnectionPort"
        },
        "32": {
          "caption": "ALPC Port",
          "references": [
            {
              "description": "Advanced Local Procedure Call (ALPC) Class",
              "url": "https://learn.microsoft.com/en-us/windows/win32/etw/alpc"
            }
          ]
        },
        "33": {
          "caption": "SAM_ALIAS",
          "references": [
            {
              "description": "Security Account Manager (SAM) objects",
              "url": "https://learn.microsoft.com/en-us/previous-versions/windows/it-pro/windows-10/security/threat-protection/auditing/audit-sam"
            }
          ]
        },
        "34": {
          "caption": "SAM_GROUP",
          "references": [
            {
              "description": "Security Account Manager (SAM) objects",
              "url": "https://learn.microsoft.com/en-us/previous-versions/windows/it-pro/windows-10/security/threat-protection/auditing/audit-sam"
            }
          ]
        },
        "35": {
          "caption": "SAM_USER",
          "references": [
            {
              "description": "Security Account Manager (SAM) objects",
              "url": "https://learn.microsoft.com/en-us/previous-versions/windows/it-pro/windows-10/security/threat-protection/auditing/audit-sam"
            }
          ]
        },
        "36": {
          "caption": "SAM_DOMAIN",
          "references": [
            {
              "description": "Security Account Manager (SAM) Domain",
              "url": "https://learn.microsoft.com/en-us/windows/win32/adschema/c-samdomain"
            }
          ]
        },
        "37": {
          "caption": "SAM_SERVER",
          "references": [
            {
              "description": "Security Account Manager (SAM) Server",
              "url": "https://learn.microsoft.com/en-us/windows/win32/adschema/c-samserver"
            }
          ]
        },
        "38": {
          "caption": "Atom",
          "references": [
            {
              "description": "Atom Types",
              "url": "https://learn.microsoft.com/en-us/windows/win32/dataxchg/about-atom-tables#atom-types"
            }
          ]
        },
        "39": {
          "caption": "WFP Filter",
          "references": [
            {
              "description": "Windows Filtering Platform (WFP) Object Model",
              "url": "https://learn.microsoft.com/en-us/windows/win32/fwp/object-model"
            }
          ]
        },
        "40": {
          "caption": "WFP Callout",
          "references": [
            {
              "description": "Windows Filtering Platform (WFP) Object Model",
              "url": "https://learn.microsoft.com/en-us/windows/win32/fwp/object-model"
            }
          ]
        },
        "41": {
          "caption": "WFP Layer",
          "references": [
            {
              "description": "Windows Filtering Platform (WFP) Object Model",
              "url": "https://learn.microsoft.com/en-us/windows/win32/fwp/object-model"
            }
          ]
        },
        "42": {
          "caption": "WFP Sub-layer",
          "references": [
            {
              "description": "Windows Filtering Platform (WFP) Object Model",
              "url": "https://learn.microsoft.com/en-us/windows/win32/fwp/object-model"
            }
          ]
        },
        "43": {
          "caption": "WFP Provider",
          "references": [
            {
              "description": "Windows Filtering Platform (WFP) Object Model",
              "url": "https://learn.microsoft.com/en-us/windows/win32/fwp/object-model"
            }
          ]
        },
        "44": {
          "caption": "WFP Provider Context",
          "references": [
            {
              "description": "Windows Filtering Platform (WFP) Object Model",
              "url": "https://learn.microsoft.com/en-us/windows/win32/fwp/object-model"
            }
          ]
        },
        "99": {
          "caption": "Other",
          "description": "The resource object type is not mapped. See the <code>type</code> attribute, which may contain a data source specific value."
        }
      }
    },
    "uid": {
      "description": "The Windows provided handle identifier for the resource object"
    }
  }
}