{
  "uid": 2,
  "caption": "Device Config State",
  "description": "Device Config State events report device configuration data and CIS Benchmark results.",
  "extends": "discovery",
  "name": "config_state",
  "attributes": {
    "actor": {
      "group": "context",
      "requirement": "optional"
    },
    "cis_benchmark_result": {
      "group": "primary",
      "requirement": "recommended"
    },
    "device": {
      "description": "The device that is being discovered by an inventory process.",
      "group": "primary",
      "requirement": "required"
    }
  },
  "profiles": [
    "host"
  ]
}