{
  "attributes": {
    "disposition_id": {
      "enum": {
        "3": {
          "name": "Does not exist"
        },
        "4": {
          "name": "Error"
        },
        "5": {
          "name": "Unsupported"
        }
      }
    },
    "request": {
      "requirement": "optional"
    }
  },
  "description": "Unsuccessful Discovery events report unsuccessful attempts at Evidence of Compromise queries.",
  "extends": "discovery",
  "name": "Unsuccessful Discovery",
  "type": "discovery_no_result",
  "uid": 500
}