{
  "uid": 18,
  "caption": "User Query",
  "description": "User Query events report user data that have been discovered, queried, polled or searched. This event differs from User Inventory as it describes the result of a targeted search by filtering a subset of user attributes.",
  "extends": "discovery_result",
  "name": "user_query",
  "@deprecated": {
    "message": "Use the <code>Live Evidence Info</code> class.",
    "since": "1.5.0"
  },
  "attributes": {
    "user": {
      "group": "primary",
      "requirement": "required"
    }
  }
}