{
  "attributes": {
    "outcome_id": {
      "enum": {
        "1": {
          "name": "Blocked"
        },
        "2": {
          "name": "Allowed"
        },
        "3": {
          "name": "No Action"
        },
        "4": {
          "name": "Logged"
        },
        "5": {
          "name": "Command Script Run"
        },
        "6": {
          "name": "Corrected"
        },
        "7": {
          "name": "Partially Corrected"
        },
        "8": {
          "name": "Uncorrected"
        },
        "9": {
          "name": "Detected"
        }
      }
    }
  },
  "description": "Boot Record Detection events report the detection and resolution of boot record malicious access.",
  "extends": "detection_event",
  "name": "Boot Record Detection",
  "type": "boot_record_detection",
  "uid": 500
}