{
  "caption": "Prefetch Info",
  "description": "Prefetch Info events report information about Windows prefetch files.",
  "extends": "discovery_result",
  "name": "prefetch_info",
  "uid": 19,
  "attributes": {
    "last_run_time": {
      "description": "The prefetch file last run time.",
      "group": "occurrence",
      "requirement": "recommended"
    },
    "name": {
      "description": "The name of the prefetch file that is the target of the query.",
      "group": "primary",
      "requirement": "required"
    },
    "run_count": {
      "group": "primary",
      "requirement": "recommended"
    }
  }
}